oak9/__init__.py
oak9/tython/__init__.py
oak9/tython/runner.py
oak9/tython/core/__init__.py
oak9/tython/core/exception.py
oak9/tython/core/findings.py
oak9/tython/core/logger.py
oak9/tython/core/proxyobjs.py
oak9/tython/core/tools.py
oak9/tython/core/types.py
oak9/tython/core/types_tests.py
oak9/tython/core/utilities.py
oak9/tython/core/bp_metadata_utils/__init__.py
oak9/tython/core/bp_metadata_utils/blueprint_docstring.py
oak9/tython/core/bp_metadata_utils/blueprint_meta_data.py
oak9/tython/core/bp_metadata_utils/customer_blueprint_repo.py
oak9/tython/core/bp_metadata_utils/customer_blueprint_repo_test.py
oak9/tython/core/bp_metadata_utils/git_utils.py
oak9/tython/core/bp_metadata_utils/multiple_policies_per_file_repo.py
oak9/tython/core/bp_metadata_utils/policy.py
oak9/tython/core/bp_metadata_utils/policy_implementation_docstring.py
oak9/tython/core/bp_metadata_utils/policy_implementation_docstring_test.py
oak9/tython/core/bp_metadata_utils/policy_repo.py
oak9/tython/core/bp_metadata_utils/policy_repo_test.py
oak9/tython/core/bp_metadata_utils/python_source_file_utils.py
oak9/tython/core/sdk/__init__.py
oak9/tython/core/sdk/helper.py
oak9/tython/core/sdk/resource_map.py
oak9/tython/core/services/__init__.py
oak9/tython/core/services/tython_api_service.py
oak9/tython/models/__init__.py
oak9/tython/models/aws/__init__.py
oak9/tython/models/aws/aws_accessanalyzer_pb2.py
oak9/tython/models/aws/aws_accessanalyzer_pb2.pyi
oak9/tython/models/aws/aws_accessanalyzer_pb2_grpc.py
oak9/tython/models/aws/aws_acmpca_pb2.py
oak9/tython/models/aws/aws_acmpca_pb2.pyi
oak9/tython/models/aws/aws_acmpca_pb2_grpc.py
oak9/tython/models/aws/aws_alexa_ask_pb2.py
oak9/tython/models/aws/aws_alexa_ask_pb2.pyi
oak9/tython/models/aws/aws_alexa_ask_pb2_grpc.py
oak9/tython/models/aws/aws_amazonmq_pb2.py
oak9/tython/models/aws/aws_amazonmq_pb2.pyi
oak9/tython/models/aws/aws_amazonmq_pb2_grpc.py
oak9/tython/models/aws/aws_amplify_pb2.py
oak9/tython/models/aws/aws_amplify_pb2.pyi
oak9_tython-1.0.13.dist-info/LICENSE
oak9_tython-1.0.13.dist-info/METADATA
oak9_tython-1.0.13.dist-info/WHEEL
oak9_tython-1.0.13.dist-info/top_level.txt
oak9_tython-1.0.13.dist-info/RECORD
