Metadata-Version: 2.1
Name: oak9-tython
Version: 1.0.13
Author: Claudio Balbin, Brandon Nicoll
Author-email: bnicoll@oak9.io
Project-URL: Homepage, https://github.com/oak9io/tython
Project-URL: Bug Tracker, https://github.com/oak9io/tython/issues
Classifier: Programming Language :: Python :: 3
Classifier: License :: OSI Approved :: Apache Software License
Classifier: Operating System :: OS Independent
Requires-Python: >=3.11
License-File: LICENSE
Requires-Dist: gitpython ==3.1.31
Requires-Dist: protobuf >=4.23.1
Requires-Dist: requests >=2.31.0
Requires-Dist: structlog >=23.1.0
